kraken/build/__init__.py
kraken/build/py.typed
kraken/build/tests/test_import.py
kraken/build/utils/import_helper.py
kraken/common/__init__.py
kraken/common/_argparse.py
kraken/common/_asciitable.py
kraken/common/_auth.py
kraken/common/_buildscript.py
kraken/common/_buildscript_test.py
kraken/common/_colored.py
kraken/common/_date.py
kraken/common/_date_test.py
kraken/common/_environment.py
kraken/common/_fs.py
kraken/common/_generic.py
kraken/common/_importlib.py
kraken/common/_option_sets.py
kraken/common/_requirements.py
kraken/common/_requirements_test.py
kraken/common/_runner.py
kraken/common/_runner_test.py
kraken/common/_terminal.py
kraken/common/_text.py
kraken/common/_text_test.py
kraken/common/_tomlconfig.py
kraken/common/_tomlconfig_test.py
kraken/common/exceptions.py
kraken/common/findpython.py
kraken/common/gitignore.py
kraken/common/graphviz.py
kraken/common/iter.py
kraken/common/path.py
kraken/common/py.typed
kraken/common/sanitize.py
kraken/common/sanitize_test.py
kraken/common/strings.py
kraken/common/supplier.py
kraken/common/toml.py
kraken/common/http/__init__.py
kraken/common/http/lint_ban_bare_requests.py
kraken/common/pyenv/__init__.py
kraken/common/pyenv/_distributions.py
kraken/common/pyenv/_virtualenv.py
kraken/core/__init__.py
kraken/core/py.typed
kraken/core/address/__init__.py
kraken/core/address/_address.py
kraken/core/address/_address_resolver.py
kraken/core/address/_address_resolver_test.py
kraken/core/address/_address_test.py
kraken/core/address/_addressable.py
kraken/core/base/__init__.py
kraken/core/base/currentable.py
kraken/core/base/metadata.py
kraken/core/cli/executor.py
kraken/core/cli/executor_test.py
kraken/core/cli/main.py
kraken/core/cli/option_sets.py
kraken/core/system/__init__.py
kraken/core/system/aspect.py
kraken/core/system/aspect_test.py
kraken/core/system/buildcache.py
kraken/core/system/context.py
kraken/core/system/context_test.py
kraken/core/system/errors.py
kraken/core/system/graph.py
kraken_build-0.50.2.dist-info/METADATA
kraken_build-0.50.2.dist-info/WHEEL
kraken_build-0.50.2.dist-info/entry_points.txt
kraken_build-0.50.2.dist-info/licenses/LICENSE
kraken_build-0.50.2.dist-info/RECORD
