Metadata-Version: 2.4
Name: kraken-build
Version: 0.50.2
Summary: Kraken is an extensible build orchestration system.
Project-URL: Bug Tracker, https://github.com/kraken-build/kraken-build/issues
Project-URL: Documentation, https://kraken-build.github.io/kraken-build/
Project-URL: Homepage, https://kraken-build.github.io/kraken-build/
Project-URL: Repository, https://github.com/kraken-build/kraken-build/
Author-email: Niklas Rosenstein <rosensteinniklas@gmail.com>
License-Expression: MIT
License-File: LICENSE
Requires-Python: <3.15,>=3.10
Requires-Dist: cyclopts<4.0.0,>=3.22.2
Requires-Dist: databind<5.0.0,>=4.5.0
Requires-Dist: deprecated>=1.2.18
Requires-Dist: httpx<0.29.0,>=0.28.0
Requires-Dist: keyring<26.0.0,>=25.0.0
Requires-Dist: loguru<0.8.0,>=0.7.2
Requires-Dist: networkx<4.0,>=3.1
Requires-Dist: packaging<25.1,>=25
Requires-Dist: stablehash>=0.2.2
Requires-Dist: termcolor<3.3,>=3.2
Requires-Dist: tomli-w<2.0.0,>=1.0.0
Requires-Dist: tomli<3.0.0,>=2.0.1
Requires-Dist: tomlkit<0.14.0,>=0.13.0
Requires-Dist: typeapi<3.0.0,>=2.3.0
Requires-Dist: typing-extensions>=4.6.0
Requires-Dist: uv<0.10.0,>=0.9.0
